[
  {
    "question": "Bonds: What is a bond? When would a bond be obtained?",
    "keyword1": "bond|bon|bod|boond|bonnd/i",
    "keyword2": "probate/i",
    "link": "http://www.wcpc.us/FAQ/bonds.htm",
    "answer": ""
  },
  {
    "question": "Personal Identifying Information (PII)",
    "keyword1": "pii/i",
    "keyword2": "pii/i",
    "link": "https://www.wcpc.us/filing.html#pii",
    "answer": ""
  },
  {
    "question": "SCAO approved forms",
    "keyword1": "scao/i",
    "keyword2": "scao/i",
    "link": "https://www.wcpc.us/probate-court-forms.html#scao",
    "answer": ""
  },
  {
    "question": "Motor Vehicles: How can a vehicle be transferred out of the decedent's name?",
    "keyword1": "motor|vehicle|bus|car|cycle|bike|scooter|aeroplane|railway/i",
    "keyword2": "sell|transfer|send/i",
    "link": "https://www.wcpc.us/FAQ/motorvehicle.htm",
    "answer": ""
  }
]